{"stats":{"minecraft:picked_up":{"minecraft:iron_chestplate":5,"minecraft:chainmail_boots":1,"minecraft:flower_pot":2,"minecraft:stone_slab":114,"minecraft:lead":6,"minecraft:smithing_table":1,"minecraft:diamond_sword":11,"minecraft:oak_stairs":299,"minecraft:enchanted_book":14,"minecraft:brewing_stand":10,"minecraft:blue_concrete":620,"minecraft:golden_sword":14,"minecraft:polished_deepslate":539,"minecraft:string":210,"minecraft:soul_soil":8,"minecraft:shroomlight":2,"minecraft:beetroot":2,"minecraft:orange_concrete_powder":215,"minecraft:diamond_leggings":9,"minecraft:cobbled_deepslate":7665,"minecraft:gold_nugget":342,"minecraft:spruce_planks":959,"minecraft:netherite_upgrade_smithing_template":2,"minecraft:hopper_minecart":16,"minecraft:golden_helmet":1,"minecraft:magenta_concrete_powder":5,"minecraft:composter":18,"minecraft:purpur_pillar":2,"minecraft:lightning_rod":3,"minecraft:deepslate_tile_stairs":109,"minecraft:golden_chestplate":1,"minecraft:cauldron":3,"minecraft:black_dye":2,"minecraft:stone_sword":19,"minecraft:red_tulip":118,"minecraft:iron_block":274,"minecraft:carved_pumpkin":35,"minecraft:glowstone":1,"minecraft:end_rod":6,"minecraft:netherite_chestplate":1,"minecraft:white_terracotta":93,"minecraft:blaze_rod":58,"minecraft:iron_bars":75,"minecraft:snowball":2,"minecraft:birch_log":150,"minecraft:furnace_minecart":4,"minecraft:magma_block":7878,"minecraft:feather":6,"minecraft:cooked_beef":27,"minecraft:water_bucket":10,"minecraft:iron_door":1,"minecraft:smoker":1,"minecraft:flint":25,"minecraft:netherite_leggings":2,"minecraft:map":6,"minecraft:pink_concrete_powder":3,"minecraft:lantern":29,"minecraft:light_gray_concrete_powder":7,"minecraft:chipped_anvil":1,"minecraft:stonecutter":29,"minecraft:diamond_helmet":15,"minecraft:glowstone_dust":73,"minecraft:chiseled_polished_blackstone":134,"minecraft:warped_wart_block":5,"minecraft:dropper":9,"minecraft:stripped_spruce_log":54,"minecraft:ink_sac":7,"minecraft:granite_slab":135,"minecraft:dead_fire_coral_fan":1,"minecraft:loom":1,"minecraft:dark_oak_log":33,"minecraft:barrel":6,"minecraft:iron_hoe":2,"minecraft:quartz_bricks":2,"minecraft:black_concrete_powder":68,"minecraft:dispenser":2,"minecraft:deepslate":725,"minecraft:lever":79,"minecraft:deepslate_gold_ore":10,"minecraft:polished_granite_slab":77,"minecraft:granite":596,"minecraft:golden_horse_armor":1,"minecraft:bread":7,"minecraft:jack_o_lantern":26,"minecraft:dark_oak_fence":1,"minecraft:crimson_roots":13,"minecraft:diamond_pickaxe":23,"minecraft:spruce_leaves":194,"minecraft:crafting_table":103,"minecraft:bubble_coral_fan":17,"minecraft:nether_wart":100,"minecraft:clay_ball":28,"minecraft:redstone_lamp":7,"minecraft:dragon_head":2,"minecraft:purpur_block":20,"minecraft:dead_horn_coral_block":1,"minecraft:cornflower":22,"minecraft:red_bed":1,"minecraft:elytra":15,"minecraft:flint_and_steel":5,"minecraft:snow":51,"minecraft:white_carpet":52451,"minecraft:white_stained_glass":4,"minecraft:iron_shovel":6,"minecraft:glass_pane":21,"minecraft:cracked_stone_bricks":210,"minecraft:cartography_table":1,"minecraft:netherite_sword":1,"minecraft:deepslate_diamond_ore":2,"minecraft:beef":7,"minecraft:poppy":1082,"minecraft:spruce_slab":387,"minecraft:minecart":197,"minecraft:chest":354,"minecraft:birch_sapling":70,"minecraft:piston":65,"minecraft:copper_ore":56,"minecraft:egg":12,"minecraft:polished_deepslate_slab":480,"minecraft:stone":11988,"minecraft:oak_door":15,"minecraft:spruce_fence":56,"minecraft:white_dye":6,"minecraft:carrot":2843,"minecraft:redstone":1241,"minecraft:netherite_pickaxe":1,"minecraft:tnt":92,"minecraft:stone_shovel":5,"minecraft:diamond_chestplate":15,"minecraft:beetroot_seeds":29,"minecraft:peony":31,"minecraft:diamond_boots":10,"minecraft:shears":6,"minecraft:deepslate_bricks":1025,"minecraft:gold_ingot":64,"minecraft:totem_of_undying":7,"minecraft:white_shulker_box":3,"minecraft:mutton":16,"minecraft:bone_block":29,"minecraft:white_wool":153,"minecraft:lime_concrete_powder":466,"minecraft:rail":726,"minecraft:oxeye_daisy":21,"minecraft:stripped_oak_log":4,"minecraft:birch_leaves":67,"minecraft:yellow_shulker_box":8,"minecraft:tripwire_hook":9,"minecraft:blackstone_slab":26,"minecraft:red_mushroom_block":2,"minecraft:red_mushroom":97,"minecraft:purpur_stairs":9,"minecraft:oak_log":1798,"minecraft:lily_pad":63,"minecraft:ancient_debris":3,"minecraft:golden_boots":4,"minecraft:paper":211,"minecraft:white_banner":1,"minecraft:apple":361,"minecraft:stone_bricks":7071,"minecraft:kelp":531,"minecraft:warped_stem":2,"minecraft:oak_fence_gate":91,"minecraft:stone_pickaxe":3,"minecraft:magenta_stained_glass":1,"minecraft:iron_sword":5,"minecraft:dark_oak_stairs":1,"minecraft:milk_bucket":1,"minecraft:yellow_concrete":809,"minecraft:lime_concrete":4,"minecraft:gravel":682,"minecraft:spruce_sapling":654,"minecraft:spruce_log":4677,"minecraft:dragon_egg":1,"minecraft:firework_rocket":321,"minecraft:diamond_shovel":12,"minecraft:coal_ore":39,"minecraft:slime_ball":533,"minecraft:stone_axe":4,"minecraft:polished_diorite":5,"minecraft:diamond_axe":9,"minecraft:redstone_ore":8,"minecraft:deepslate_redstone_ore":1,"minecraft:warped_roots":3,"minecraft:oak_button":13,"minecraft:crimson_nylium":15,"minecraft:hopper":552,"minecraft:ender_pearl":5549,"minecraft:shulker_shell":19,"minecraft:chiseled_deepslate":2,"minecraft:wheat":151,"minecraft:nether_brick_fence":33,"minecraft:redstone_block":29,"minecraft:ender_chest":45,"minecraft:iron_trapdoor":11,"minecraft:light_gray_shulker_box":91,"minecraft:dead_horn_coral_fan":30,"minecraft:potion":21,"minecraft:stone_brick_stairs":394,"minecraft:raw_copper":496,"minecraft:deepslate_lapis_ore":10,"minecraft:smooth_stone_slab":25,"minecraft:iron_leggings":4,"minecraft:sticky_piston":129,"minecraft:pink_shulker_box":25,"minecraft:oak_sign":23,"minecraft:deepslate_tiles":133,"minecraft:smooth_stone":551,"minecraft:comparator":61,"minecraft:bucket":39,"minecraft:white_tulip":75,"minecraft:red_dye":1,"minecraft:rose_bush":59,"minecraft:redstone_torch":98,"minecraft:cobblestone_slab":451,"minecraft:ender_eye":7,"minecraft:iron_pickaxe":8,"minecraft:deepslate_tile_wall":71,"minecraft:deepslate_iron_ore":5,"minecraft:iron_boots":3,"minecraft:furnace":138,"minecraft:tipped_arrow":91,"minecraft:stick":2079,"minecraft:orange_shulker_box":162,"minecraft:deepslate_brick_wall":18,"minecraft:oak_fence":23,"minecraft:torch":324,"minecraft:spruce_stairs":282,"minecraft:porkchop":70,"minecraft:target":27,"minecraft:netherite_shovel":3,"minecraft:pointed_dripstone":80,"minecraft:diorite":127,"minecraft:vine":20,"minecraft:yellow_concrete_powder":15,"minecraft:quartz_block":59,"minecraft:rotten_flesh":413,"minecraft:deepslate_copper_ore":4,"minecraft:fire_coral_fan":1,"minecraft:deepslate_brick_stairs":403,"minecraft:obsidian":195,"minecraft:cobblestone":7440,"minecraft:nautilus_shell":1,"minecraft:pink_petals":12,"minecraft:leather_chestplate":1,"minecraft:lilac":61,"minecraft:magma_cream":8,"minecraft:repeater":103,"minecraft:dead_tube_coral_fan":2,"minecraft:andesite":281,"minecraft:golden_leggings":2,"minecraft:beacon":3,"minecraft:potato":14,"minecraft:tuff":130,"minecraft:light_gray_dye":1,"minecraft:wither_skeleton_skull":5,"minecraft:lapis_lazuli":212,"minecraft:dirt":11011,"minecraft:name_tag":1,"minecraft:glass":2260,"minecraft:bone":2596,"minecraft:cobbled_deepslate_slab":6,"minecraft:bow":23,"minecraft:wheat_seeds":717,"minecraft:orange_tulip":130,"minecraft:deepslate_brick_slab":146,"minecraft:raw_gold":64,"minecraft:bell":2,"minecraft:grindstone":2,"minecraft:netherite_axe":2,"minecraft:mossy_stone_bricks":260,"minecraft:fletching_table":3,"minecraft:bamboo":1111,"minecraft:powered_rail":402,"minecraft:oak_planks":893,"minecraft:cooked_porkchop":11,"minecraft:music_disc_13":1,"minecraft:jungle_planks":2,"minecraft:sand":2761,"minecraft:cyan_bed":1,"minecraft:grass_block":7903,"minecraft:lily_of_the_valley":80,"minecraft:shulker_box":64,"minecraft:mossy_cobblestone":52,"minecraft:spruce_fence_gate":39,"minecraft:clay":10,"minecraft:diamond":25,"minecraft:netherite_helmet":3,"minecraft:slime_block":241,"minecraft:spruce_boat":10,"minecraft:black_concrete":93,"minecraft:crossbow":6,"minecraft:bone_meal":482,"minecraft:golden_apple":65,"minecraft:spruce_sign":18,"minecraft:emerald":274,"minecraft:chorus_fruit":45,"minecraft:oak_sapling":2875,"minecraft:netherrack":8307,"minecraft:oak_leaves":350,"minecraft:andesite_slab":66,"minecraft:nether_star":1,"minecraft:end_stone_bricks":15,"minecraft:fishing_rod":1,"minecraft:allium":2,"minecraft:azure_bluet":40,"minecraft:chicken":3,"minecraft:ladder":180,"minecraft:brown_mushroom":21,"minecraft:packed_ice":7,"minecraft:wooden_pickaxe":2,"minecraft:stone_brick_wall":161,"minecraft:gold_block":181,"minecraft:diorite_slab":403,"minecraft:diamond_horse_armor":1,"minecraft:chain":2,"minecraft:shield":26,"minecraft:oak_trapdoor":77,"minecraft:iron_axe":5,"minecraft:item_frame":27,"minecraft:blackstone":237,"minecraft:detector_rail":111,"minecraft:spire_armor_trim_smithing_template":3,"minecraft:oak_boat":92,"minecraft:observer":119,"minecraft:lectern":201,"minecraft:sugar_cane":1497,"minecraft:blue_shulker_box":28,"minecraft:spruce_trapdoor":403,"minecraft:phantom_membrane":40,"minecraft:dark_oak_sapling":4,"minecraft:raw_iron":121,"minecraft:end_stone":2326,"minecraft:copper_ingot":3,"minecraft:note_block":12,"minecraft:stone_button":3,"minecraft:magenta_shulker_box":49,"minecraft:stone_pressure_plate":7,"minecraft:blue_concrete_powder":90,"minecraft:arrow":410,"minecraft:tube_coral":6,"minecraft:red_shulker_box":73,"minecraft:pumpkin_pie":9,"minecraft:jungle_stairs":2,"minecraft:nether_bricks":571,"minecraft:pink_tulip":66,"minecraft:saddle":2,"minecraft:netherite_boots":1,"minecraft:basalt":281,"minecraft:crimson_stem":3,"minecraft:golden_carrot":328,"minecraft:glow_ink_sac":3,"minecraft:salmon":1,"minecraft:leather":43,"minecraft:birch_planks":38,"minecraft:crimson_fungus":1,"minecraft:chainmail_chestplate":2,"minecraft:nether_wart_block":20,"minecraft:gunpowder":86,"minecraft:yellow_bed":13,"minecraft:cobblestone_wall":32,"minecraft:cobblestone_stairs":31,"minecraft:deepslate_tile_slab":106,"minecraft:cooked_mutton":4,"minecraft:podzol":312,"minecraft:iron_ingot":708,"minecraft:cooked_chicken":3,"minecraft:stripped_oak_wood":2,"minecraft:soul_sand":77,"minecraft:book":6,"minecraft:scaffolding":1350,"minecraft:oak_slab":181,"minecraft:red_concrete_powder":67,"minecraft:birch_boat":16,"minecraft:pumpkin":61,"minecraft:stone_brick_slab":364,"minecraft:quartz":470,"minecraft:dandelion":51,"minecraft:dripstone_block":24,"minecraft:lava_bucket":67,"minecraft:blast_furnace":1,"minecraft:white_bed":67,"minecraft:nether_brick_slab":99,"minecraft:spruce_door":5,"minecraft:mossy_stone_brick_slab":15,"minecraft:spider_eye":48,"minecraft:light_blue_concrete_powder":9,"minecraft:pumpkin_seeds":300,"minecraft:lime_dye":2,"minecraft:white_concrete_powder":155,"minecraft:chainmail_leggings":1,"minecraft:iron_helmet":5,"minecraft:terracotta":2,"minecraft:netherite_hoe":1,"minecraft:end_stone_brick_slab":146,"minecraft:coal":763},"minecraft:used":{"minecraft:peony":1,"minecraft:chiseled_deepslate":17,"minecraft:dispenser":4,"minecraft:ladder":206,"minecraft:elytra":105,"minecraft:spruce_slab":896,"minecraft:poppy":12,"minecraft:chest":708,"minecraft:stone":540,"minecraft:white_shulker_box":3,"minecraft:soul_sand":51,"minecraft:deepslate_brick_slab":538,"minecraft:snowball":2,"minecraft:azure_bluet":3,"minecraft:stripped_spruce_log":44,"minecraft:spruce_boat":14,"minecraft:packed_ice":10,"minecraft:lava_bucket":258,"minecraft:netherite_shovel":1750,"minecraft:grass_block":5462,"minecraft:birch_sapling":47,"minecraft:copper_ore":1,"minecraft:orange_shulker_box":157,"minecraft:quartz_block":40,"minecraft:netherite_hoe":276,"minecraft:stone_brick_stairs":879,"minecraft:bow":33,"minecraft:furnace":142,"minecraft:oak_sapling":1993,"minecraft:egg":4,"minecraft:dragon_head":1,"minecraft:magenta_shulker_box":48,"minecraft:deepslate_brick_wall":224,"minecraft:diorite":17,"minecraft:mossy_stone_bricks":12,"minecraft:powered_rail":363,"minecraft:spruce_door":5,"minecraft:chorus_fruit":10,"minecraft:blackstone":16,"minecraft:lime_concrete_powder":7,"minecraft:wooden_pickaxe":25,"minecraft:composter":17,"minecraft:oak_leaves":154,"minecraft:sand":73,"minecraft:blast_furnace":1,"minecraft:netherite_helmet":1,"minecraft:black_concrete_powder":14,"minecraft:deepslate_brick_stairs":981,"minecraft:pumpkin_seeds":44,"minecraft:lightning_rod":6,"minecraft:deepslate_tiles":267,"minecraft:stone_button":3,"minecraft:lectern":193,"minecraft:diamond_sword":4053,"minecraft:dark_oak_fence":1,"minecraft:white_stained_glass":579,"minecraft:oak_boat":79,"minecraft:oak_trapdoor":156,"minecraft:diorite_slab":403,"minecraft:iron_bars":28,"minecraft:stone_sword":6,"minecraft:carved_pumpkin":1,"minecraft:torch":943,"minecraft:netherrack":5620,"minecraft:light_gray_shulker_box":91,"minecraft:dragon_egg":1,"minecraft:brewing_stand":6,"minecraft:target":9,"minecraft:ancient_debris":1,"minecraft:nether_brick_slab":103,"minecraft:polished_granite_slab":77,"minecraft:oak_fence_gate":297,"minecraft:polished_diorite":36,"minecraft:red_shulker_box":70,"minecraft:iron_block":189,"minecraft:iron_axe":3157,"minecraft:spruce_button":3,"minecraft:slime_block":252,"minecraft:totem_of_undying":3,"minecraft:diamond_chestplate":97,"minecraft:barrel":6,"minecraft:tripwire_hook":53,"minecraft:glowstone":27,"minecraft:basalt":3,"minecraft:lime_concrete":1,"minecraft:iron_trapdoor":9,"minecraft:goat_horn":14,"minecraft:pointed_dripstone":26,"minecraft:cobbled_deepslate":314,"minecraft:horn_coral_fan":12,"minecraft:observer":153,"minecraft:wheat_seeds":120,"minecraft:water_bucket":1034,"minecraft:yellow_shulker_box":8,"minecraft:bubble_coral_fan":7,"minecraft:blue_concrete_powder":23,"minecraft:cauldron":26,"minecraft:deepslate_bricks":2048,"minecraft:fletching_table":6,"minecraft:spruce_fence_gate":87,"minecraft:vine":16,"minecraft:rail":712,"minecraft:red_bed":1,"minecraft:mossy_cobblestone":1,"minecraft:polished_deepslate_slab":375,"minecraft:tnt":25,"minecraft:comparator":53,"minecraft:crafting_table":92,"minecraft:oak_slab":94,"minecraft:white_bed":84,"minecraft:cake":7,"minecraft:spruce_log":311,"minecraft:deepslate_tile_wall":7,"minecraft:oak_log":459,"minecraft:ender_eye":2,"minecraft:diamond_pickaxe":51168,"minecraft:cornflower":1,"minecraft:diamond_shovel":20393,"minecraft:oak_button":70,"minecraft:iron_pickaxe":739,"minecraft:leather_helmet":1,"minecraft:magenta_concrete_powder":8,"minecraft:spruce_trapdoor":956,"minecraft:spruce_sapling":483,"minecraft:cobblestone":3680,"minecraft:potion":4,"minecraft:cooked_porkchop":74,"minecraft:red_concrete_powder":13,"minecraft:porkchop":4,"minecraft:dandelion":4,"minecraft:kelp":239,"minecraft:diamond_leggings":4,"minecraft:iron_shovel":977,"minecraft:polished_deepslate":66,"minecraft:dead_tube_coral_fan":2,"minecraft:oak_sign":33,"minecraft:white_concrete_powder":8,"minecraft:shield":74,"minecraft:nether_wart":24,"minecraft:bell":2,"minecraft:mossy_stone_brick_slab":15,"minecraft:spruce_leaves":128,"minecraft:jungle_planks":1,"minecraft:nether_bricks":289,"minecraft:carrot":1523,"minecraft:deepslate_tile_slab":446,"minecraft:furnace_minecart":4,"minecraft:tuff":67,"minecraft:obsidian":111,"minecraft:glass":3451,"minecraft:lantern":49,"minecraft:iron_helmet":1,"minecraft:hopper_minecart":24,"minecraft:stone_bricks":13506,"minecraft:item_frame":63,"minecraft:repeater":126,"minecraft:redstone_lamp":6,"minecraft:magma_block":2419,"minecraft:scaffolding":1140,"minecraft:blue_shulker_box":28,"minecraft:gold_block":204,"minecraft:pink_concrete_powder":4,"minecraft:fire_coral_fan":1,"minecraft:diamond_boots":7,"minecraft:chiseled_polished_blackstone":153,"minecraft:tube_coral_fan":1,"minecraft:dropper":36,"minecraft:wither_skeleton_skull":4,"minecraft:stone_pickaxe":190,"minecraft:birch_leaves":4,"minecraft:oak_planks":231,"minecraft:ender_pearl":206,"minecraft:redstone_block":36,"minecraft:end_stone_brick_slab":146,"minecraft:sugar_cane":160,"minecraft:diamond_axe":6702,"minecraft:white_wool":1,"minecraft:yellow_concrete":186,"minecraft:crossbow":85,"minecraft:stone_brick_wall":620,"minecraft:note_block":14,"minecraft:end_stone":1582,"minecraft:shears":475,"minecraft:sticky_piston":158,"minecraft:redstone_torch":114,"minecraft:dead_fire_coral_fan":1,"minecraft:lever":82,"minecraft:firework_rocket":733,"minecraft:deepslate":18,"minecraft:string":239,"minecraft:gravel":71,"minecraft:blackstone_slab":26,"minecraft:granite_slab":133,"minecraft:light_blue_concrete_powder":13,"minecraft:dead_horn_coral_fan":28,"minecraft:andesite":87,"minecraft:grindstone":3,"minecraft:bone_meal":481,"minecraft:smooth_stone_slab":100,"minecraft:experience_bottle":2,"minecraft:oak_fence":3,"minecraft:orange_concrete_powder":5,"minecraft:white_tulip":2,"minecraft:flint_and_steel":257,"minecraft:redstone_ore":8,"minecraft:stone_shovel":187,"minecraft:redstone":495,"minecraft:dried_kelp":3,"minecraft:spruce_planks":934,"minecraft:ender_chest":40,"minecraft:cooked_chicken":29,"minecraft:oak_door":3,"minecraft:dirt":10496,"minecraft:white_carpet":180,"minecraft:hopper":645,"minecraft:spruce_stairs":452,"minecraft:cobblestone_wall":18,"minecraft:diamond_helmet":4,"minecraft:shulker_box":64,"minecraft:spruce_fence":73,"minecraft:granite":40,"minecraft:iron_hoe":167,"minecraft:wooden_axe":31,"minecraft:stone_brick_slab":293,"minecraft:bookshelf":1,"minecraft:oak_stairs":10,"minecraft:yellow_concrete_powder":15,"minecraft:light_gray_wool":1,"minecraft:golden_carrot":400,"minecraft:deepslate_tile_stairs":72,"minecraft:minecart":134,"minecraft:netherite_pickaxe":205,"minecraft:stone_pressure_plate":14,"minecraft:cooked_beef":29,"minecraft:enchanted_golden_apple":1,"minecraft:pumpkin":4,"minecraft:iron_leggings":1,"minecraft:cooked_mutton":4,"minecraft:quartz_bricks":2,"minecraft:cobblestone_stairs":15,"minecraft:spruce_sign":14,"minecraft:glass_bottle":21,"minecraft:brown_mushroom":3,"minecraft:birch_boat":16,"minecraft:andesite_slab":30,"minecraft:white_dye":1,"minecraft:beacon":2,"minecraft:stonecutter":37,"minecraft:cobblestone_slab":399,"minecraft:red_mushroom":6,"minecraft:light_gray_concrete_powder":10,"minecraft:piston":82,"minecraft:wooden_hoe":12,"minecraft:apple":108,"minecraft:netherite_axe":191,"minecraft:detector_rail":48,"minecraft:stone_slab":45,"minecraft:stone_axe":119,"minecraft:fishing_rod":16,"minecraft:bucket":1317,"minecraft:pink_shulker_box":25,"minecraft:pumpkin_pie":211,"minecraft:yellow_bed":8,"minecraft:smooth_stone":705},"minecraft:killed":{"minecraft:shulker":35,"minecraft:skeleton":77,"minecraft:chicken":2,"minecraft:magma_cube":11,"minecraft:iron_golem":44,"minecraft:pillager":32,"minecraft:zombie":193,"minecraft:cow":17,"minecraft:endermite":2,"minecraft:wandering_trader":2,"minecraft:frog":1,"minecraft:enderman":6048,"minecraft:zombified_piglin":2,"minecraft:witch":36,"minecraft:spider":62,"minecraft:wither":1,"minecraft:piglin":49,"minecraft:pig":27,"minecraft:zombie_villager":6,"minecraft:creeper":34,"minecraft:sheep":11,"minecraft:trader_llama":3,"minecraft:ghast":1,"minecraft:blaze":132,"minecraft:slime":226,"minecraft:phantom":29,"minecraft:drowned":11,"minecraft:bat":2,"minecraft:hoglin":5,"minecraft:squid":4,"minecraft:wither_skeleton":119,"minecraft:villager":183},"minecraft:killed_by":{"minecraft:piglin":3,"minecraft:blaze":1,"minecraft:player":2,"minecraft:iron_golem":2,"minecraft:skeleton":2},"minecraft:crafted":{"minecraft:ender_chest":2,"minecraft:black_dye":2,"minecraft:light_gray_concrete_powder":8,"minecraft:oak_sign":24,"minecraft:cut_sandstone_slab":12,"minecraft:blaze_powder":10,"minecraft:birch_boat":1,"minecraft:slime_block":36,"minecraft:lever":34,"minecraft:diamond_shovel":1,"minecraft:bookshelf":20,"minecraft:shulker_box":9,"minecraft:cooked_mutton":7,"minecraft:iron_bars":48,"minecraft:red_concrete_powder":16,"minecraft:magenta_shulker_box":1,"minecraft:glass":1723,"minecraft:diamond_helmet":1,"minecraft:repeater":39,"minecraft:diamond_leggings":3,"minecraft:magenta_concrete_powder":8,"minecraft:light_blue_concrete_powder":8,"minecraft:stone_pressure_plate":17,"minecraft:dried_kelp_block":5,"minecraft:magenta_dye":4,"minecraft:name_tag":1,"minecraft:lime_concrete_powder":8,"minecraft:glass_bottle":126,"minecraft:furnace_minecart":1,"minecraft:redstone_lamp":1,"minecraft:target":9,"minecraft:emerald":624,"minecraft:cooked_porkchop":30,"minecraft:diamond_axe":2,"minecraft:spruce_door":12,"minecraft:sticky_piston":28,"minecraft:fletching_table":3,"minecraft:hay_block":9,"minecraft:end_stone_brick_slab":150,"minecraft:stone_brick_stairs":24,"minecraft:lectern":7,"minecraft:wooden_hoe":1,"minecraft:stone_slab":252,"minecraft:iron_pickaxe":3,"minecraft:iron_block":2143,"minecraft:light_blue_bed":1,"minecraft:gold_ingot":1749,"minecraft:light_gray_dye":2,"minecraft:composter":8,"minecraft:spruce_fence_gate":116,"minecraft:golden_carrot":378,"minecraft:stone_shovel":1,"minecraft:orange_shulker_box":2,"minecraft:bone_meal":9199,"minecraft:blue_shulker_box":1,"minecraft:spruce_fence":186,"minecraft:pink_dye":4,"minecraft:white_carpet":159,"minecraft:spruce_stairs":388,"minecraft:detector_rail":78,"minecraft:deepslate_brick_wall":48,"minecraft:light_gray_shulker_box":1,"minecraft:black_concrete_powder":8,"minecraft:ladder":246,"minecraft:spruce_slab":1098,"minecraft:red_shulker_box":1,"minecraft:ender_pearl":3,"minecraft:stone_pickaxe":3,"minecraft:diamond_boots":3,"minecraft:spruce_boat":6,"minecraft:redstone_block":8,"minecraft:dark_oak_planks":132,"minecraft:chainmail_leggings":12,"minecraft:purpur_slab":48,"minecraft:enchanting_table":1,"minecraft:dried_kelp":46,"minecraft:deepslate_brick_slab":234,"minecraft:polished_granite":32,"minecraft:glowstone":11,"minecraft:white_stained_glass":776,"minecraft:enchanted_book":6,"minecraft:orange_dye":3,"minecraft:oak_fence_gate":187,"minecraft:golden_apple":2,"minecraft:andesite_slab":252,"minecraft:chainmail_boots":1,"minecraft:fermented_spider_eye":6,"minecraft:wooden_axe":1,"minecraft:iron_shovel":6,"minecraft:iron_leggings":4,"minecraft:white_bed":34,"minecraft:note_block":5,"minecraft:grindstone":2,"minecraft:oak_planks":6916,"minecraft:cobblestone_slab":456,"minecraft:barrel":3,"minecraft:polished_granite_slab":60,"minecraft:cooked_chicken":1,"minecraft:pink_shulker_box":1,"minecraft:lightning_rod":3,"minecraft:mossy_stone_brick_slab":48,"minecraft:stone":180,"minecraft:cobblestone_stairs":16,"minecraft:spruce_pressure_plate":1,"minecraft:warped_planks":8,"minecraft:cake":7,"minecraft:hopper":315,"minecraft:stone_brick_slab":150,"minecraft:bow":17,"minecraft:iron_boots":3,"minecraft:comparator":17,"minecraft:chest":724,"minecraft:oak_button":7,"minecraft:rail":608,"minecraft:blue_concrete_powder":8,"minecraft:stone_bricks":56,"minecraft:dropper":38,"minecraft:oak_slab":258,"minecraft:item_frame":38,"minecraft:cauldron":26,"minecraft:crafting_table":53,"minecraft:spruce_planks":14235,"minecraft:wooden_pickaxe":3,"minecraft:iron_helmet":17,"minecraft:chainmail_chestplate":9,"minecraft:hopper_minecart":14,"minecraft:chiseled_polished_blackstone":1,"minecraft:gold_block":265,"minecraft:birch_planks":404,"minecraft:dispenser":2,"minecraft:tnt":8,"minecraft:spruce_trapdoor":1158,"minecraft:book":21,"minecraft:iron_chestplate":1,"minecraft:paper":891,"minecraft:yellow_dye":1,"minecraft:charcoal":1,"minecraft:shield":2,"minecraft:stick":18256,"minecraft:light_blue_dye":2,"minecraft:iron_ingot":3697,"minecraft:redstone_torch":161,"minecraft:shears":5,"minecraft:deepslate_tile_slab":306,"minecraft:nether_brick_slab":24,"minecraft:redstone":460,"minecraft:fishing_rod":1,"minecraft:stone_brick_wall":13,"minecraft:tripwire_hook":46,"minecraft:furnace":70,"minecraft:stone_button":2,"minecraft:blast_furnace":1,"minecraft:piston":65,"minecraft:flint_and_steel":8,"minecraft:oak_trapdoor":208,"minecraft:end_stone_bricks":76,"minecraft:yellow_shulker_box":1,"minecraft:white_concrete_powder":8,"minecraft:polished_deepslate":1,"minecraft:iron_axe":27,"minecraft:iron_hoe":2,"minecraft:slime_ball":36,"minecraft:orange_concrete_powder":8,"minecraft:lime_dye":3,"minecraft:cobblestone_wall":12,"minecraft:minecart":39,"minecraft:observer":64,"minecraft:cooked_beef":1,"minecraft:sugar":30,"minecraft:red_dye":323,"minecraft:iron_trapdoor":5,"minecraft:spruce_sign":12,"minecraft:pink_concrete_powder":8,"minecraft:powered_rail":192,"minecraft:bucket":78,"minecraft:stone_axe":2,"minecraft:bread":11,"minecraft:air":0,"minecraft:blue_dye":3,"minecraft:oak_boat":17,"minecraft:white_wool":165,"minecraft:gold_nugget":2241,"minecraft:white_dye":202,"minecraft:stonecutter":4,"minecraft:pumpkin_pie":24,"minecraft:torch":736,"minecraft:diorite_slab":252,"minecraft:granite_slab":168,"minecraft:lapis_lazuli":11,"minecraft:diamond_chestplate":2,"minecraft:firework_rocket":1284},"minecraft:dropped":{"minecraft:iron_sword":3,"minecraft:piston":5,"minecraft:porkchop":2,"minecraft:lapis_lazuli":49,"minecraft:glow_ink_sac":3,"minecraft:glass_bottle":4,"minecraft:crafting_table":21,"minecraft:lime_concrete_powder":66,"minecraft:cooked_porkchop":26,"minecraft:orange_tulip":46,"minecraft:crossbow":4,"minecraft:warped_roots":3,"minecraft:cracked_stone_bricks":104,"minecraft:saddle":1,"minecraft:purpur_stairs":9,"minecraft:bubble_coral_fan":17,"minecraft:elytra":6,"minecraft:rail":87,"minecraft:cut_sandstone_slab":12,"minecraft:item_frame":2,"minecraft:emerald":174,"minecraft:gold_block":122,"minecraft:red_shulker_box":1,"minecraft:dirt":1018,"minecraft:stone_button":2,"minecraft:jack_o_lantern":23,"minecraft:netherite_boots":1,"minecraft:chain":1,"minecraft:gold_nugget":121,"minecraft:bone_meal":449,"minecraft:phantom_membrane":19,"minecraft:sand":1033,"minecraft:iron_pickaxe":5,"minecraft:fishing_rod":1,"minecraft:diorite_slab":252,"minecraft:white_wool":39,"minecraft:bone":2292,"minecraft:oak_door":3,"minecraft:note_block":1,"minecraft:stone_axe":2,"minecraft:sugar_cane":135,"minecraft:lever":20,"minecraft:cooked_chicken":2,"minecraft:golden_chestplate":1,"minecraft:detector_rail":2,"minecraft:cobbled_deepslate":599,"minecraft:pink_dye":1,"minecraft:netherite_sword":1,"minecraft:wheat":21,"minecraft:obsidian":8,"minecraft:rotten_flesh":803,"minecraft:oak_planks":59,"minecraft:glowstone_dust":3,"minecraft:netherite_shovel":2,"minecraft:lime_dye":2,"minecraft:end_stone":706,"minecraft:nether_brick_fence":4,"minecraft:azure_bluet":5,"minecraft:white_bed":1,"minecraft:salmon":1,"minecraft:deepslate_tiles":10,"minecraft:deepslate_copper_ore":2,"minecraft:coal_ore":20,"minecraft:jungle_stairs":2,"minecraft:hopper":109,"minecraft:ladder":129,"minecraft:white_dye":6,"minecraft:spruce_slab":7,"minecraft:end_stone_bricks":4,"minecraft:glass":689,"minecraft:beef":60,"minecraft:podzol":117,"minecraft:warped_wart_block":5,"minecraft:stone_brick_stairs":83,"minecraft:lectern":3,"minecraft:egg":2,"minecraft:enchanted_book":16,"minecraft:golden_boots":3,"minecraft:iron_ingot":399,"minecraft:orange_shulker_box":2,"minecraft:netherite_pickaxe":1,"minecraft:black_dye":1,"minecraft:wheat_seeds":143,"minecraft:deepslate_redstone_ore":1,"minecraft:tnt":69,"minecraft:golden_horse_armor":1,"minecraft:dripstone_block":24,"minecraft:deepslate_diamond_ore":2,"minecraft:netherite_chestplate":1,"minecraft:netherite_helmet":3,"minecraft:end_stone_brick_slab":150,"minecraft:purpur_slab":48,"minecraft:oak_fence":2,"minecraft:iron_helmet":11,"minecraft:feather":4,"minecraft:cobblestone":3062,"minecraft:book":10,"minecraft:apple":36,"minecraft:granite":301,"minecraft:deepslate_tile_slab":9,"minecraft:coal":245,"minecraft:golden_apple":53,"minecraft:oxeye_daisy":1,"minecraft:lava_bucket":2,"minecraft:iron_trapdoor":2,"minecraft:golden_carrot":143,"minecraft:wooden_hoe":1,"minecraft:wooden_axe":1,"minecraft:rose_bush":1,"minecraft:diamond_helmet":2,"minecraft:potion":7,"minecraft:oak_stairs":16,"minecraft:pumpkin":39,"minecraft:orange_concrete_powder":13,"minecraft:red_dye":1,"minecraft:smooth_stone":3389,"minecraft:iron_shovel":2,"minecraft:chainmail_leggings":1,"minecraft:paper":33,"minecraft:string":26,"minecraft:lily_pad":48,"minecraft:magenta_shulker_box":1,"minecraft:spruce_sapling":4,"minecraft:stone_brick_slab":244,"minecraft:pink_tulip":9,"minecraft:purpur_pillar":2,"minecraft:furnace":28,"minecraft:netherite_hoe":2,"minecraft:stone_sword":17,"minecraft:cobblestone_wall":25,"minecraft:deepslate":677,"minecraft:stone_shovel":1,"minecraft:polished_deepslate_slab":299,"minecraft:chicken":3,"minecraft:white_carpet":4075,"minecraft:clay_ball":20,"minecraft:iron_boots":4,"minecraft:blue_concrete":620,"minecraft:slime_block":16,"minecraft:stone_slab":248,"minecraft:cobbled_deepslate_slab":5,"minecraft:nether_bricks":1,"minecraft:spruce_fence":40,"minecraft:oak_sign":3,"minecraft:shears":4,"minecraft:pumpkin_seeds":160,"minecraft:target":9,"minecraft:diamond_sword":2,"minecraft:cobblestone_slab":179,"minecraft:potato":42,"minecraft:spruce_boat":3,"minecraft:stone":6750,"minecraft:flower_pot":2,"minecraft:spruce_trapdoor":197,"minecraft:spruce_planks":476,"minecraft:diamond_pickaxe":11,"minecraft:carved_pumpkin":33,"minecraft:stone_pressure_plate":1,"minecraft:stone_bricks":2972,"minecraft:spider_eye":8,"minecraft:magenta_concrete_powder":1,"minecraft:birch_boat":1,"minecraft:bow":8,"minecraft:magenta_dye":2,"minecraft:red_tulip":30,"minecraft:magma_block":1759,"minecraft:cyan_bed":1,"minecraft:pink_concrete_powder":3,"minecraft:crimson_nylium":15,"minecraft:spruce_sign":6,"minecraft:soul_sand":1,"minecraft:dark_oak_stairs":1,"minecraft:birch_planks":18,"minecraft:diamond_axe":3,"minecraft:polished_granite_slab":60,"minecraft:oak_log":659,"minecraft:ender_pearl":17150,"minecraft:nether_star":1,"minecraft:blue_concrete_powder":2,"minecraft:deepslate_tile_wall":64,"minecraft:leather":8,"minecraft:jungle_planks":1,"minecraft:flint":11,"minecraft:cobblestone_stairs":8,"minecraft:deepslate_tile_stairs":63,"minecraft:deepslate_gold_ore":10,"minecraft:cornflower":13,"minecraft:crimson_roots":12,"minecraft:cut_sandstone":1,"minecraft:pumpkin_pie":1,"minecraft:tube_coral":4,"minecraft:black_concrete":93,"minecraft:birch_log":1,"minecraft:cauldron":2,"minecraft:gold_ingot":5,"minecraft:gravel":327,"minecraft:white_tulip":24,"minecraft:blackstone":38,"minecraft:purpur_block":2,"minecraft:andesite_slab":252,"minecraft:beetroot":5,"minecraft:diamond_shovel":9,"minecraft:mossy_stone_brick_slab":48,"minecraft:cooked_mutton":4,"minecraft:carrot":1116,"minecraft:chainmail_chestplate":4,"minecraft:poppy":2190,"minecraft:leather_chestplate":1,"minecraft:gunpowder":19,"minecraft:dropper":6,"minecraft:beetroot_seeds":23,"minecraft:spruce_pressure_plate":1,"minecraft:stone_brick_wall":52,"minecraft:chest":5,"minecraft:chainmail_boots":1,"minecraft:arrow":92,"minecraft:basalt":75,"minecraft:iron_bars":66,"minecraft:powered_rail":1,"minecraft:light_gray_concrete_powder":1,"minecraft:white_concrete_powder":1,"minecraft:scaffolding":234,"minecraft:quartz":269,"minecraft:oak_leaves":14,"minecraft:splash_potion":9,"minecraft:netherrack":2259,"minecraft:firework_rocket":124,"minecraft:water_bucket":3,"minecraft:bread":25,"minecraft:lilac":29,"minecraft:deepslate_iron_ore":10,"minecraft:mossy_cobblestone":5,"minecraft:minecart":30,"minecraft:yellow_concrete":602,"minecraft:diamond_leggings":2,"minecraft:netherite_axe":1,"minecraft:observer":9,"minecraft:hopper_minecart":4,"minecraft:light_blue_concrete_powder":2,"minecraft:copper_ingot":3,"minecraft:dead_horn_coral_block":1,"minecraft:grass_block":406,"minecraft:stick":710,"minecraft:spruce_fence_gate":25,"minecraft:iron_block":128,"minecraft:deepslate_brick_stairs":86,"minecraft:milk_bucket":1,"minecraft:diorite":68,"minecraft:brewing_stand":2,"minecraft:torch":31,"minecraft:nether_wart_block":3,"minecraft:light_gray_shulker_box":1,"minecraft:yellow_shulker_box":1,"minecraft:iron_door":1,"minecraft:iron_leggings":3,"minecraft:granite_slab":170,"minecraft:iron_axe":15,"minecraft:pink_petals":1,"minecraft:bucket":11,"minecraft:dandelion":16,"minecraft:redstone":451,"minecraft:polished_deepslate":2,"minecraft:nether_brick_slab":18,"minecraft:kelp":154,"minecraft:oak_trapdoor":61,"minecraft:ender_chest":2,"minecraft:raw_copper":360,"minecraft:lime_concrete":2,"minecraft:tuff":35,"minecraft:raw_iron":79,"minecraft:composter":6,"minecraft:comparator":11,"minecraft:iron_hoe":1,"minecraft:ender_eye":7,"minecraft:totem_of_undying":3,"minecraft:shulker_box":1,"minecraft:glass_pane":3,"minecraft:netherite_leggings":2,"minecraft:flint_and_steel":3,"minecraft:deepslate_bricks":571,"minecraft:copper_ore":35,"minecraft:shield":6,"minecraft:black_concrete_powder":2,"minecraft:diamond_chestplate":5,"minecraft:andesite":153,"minecraft:mossy_stone_bricks":91,"minecraft:golden_leggings":3,"minecraft:oak_boat":10,"minecraft:oak_sapling":392,"minecraft:golden_sword":346,"minecraft:slime_ball":17,"minecraft:diamond_boots":1,"minecraft:spruce_log":915,"minecraft:beacon":1,"minecraft:stone_pickaxe":4,"minecraft:wooden_pickaxe":5,"minecraft:raw_gold":9},"minecraft:mined":{"minecraft:dead_horn_coral_fan":1,"minecraft:polished_granite_slab":6,"minecraft:dragon_wall_head":1,"minecraft:red_shulker_box":71,"minecraft:white_bed":61,"minecraft:obsidian":160,"minecraft:carved_pumpkin":2,"minecraft:granite":351,"minecraft:chiseled_polished_blackstone":54,"minecraft:deepslate_tile_wall":7,"minecraft:stone_brick_wall":154,"minecraft:deepslate_bricks":522,"minecraft:purpur_slab":1,"minecraft:deepslate_tile_stairs":46,"minecraft:hopper":446,"minecraft:crimson_fungus":1,"minecraft:oxeye_daisy":5,"minecraft:oak_wall_sign":13,"minecraft:nether_wart":24,"minecraft:spawner":1,"minecraft:tall_seagrass":18,"minecraft:magma_block":5357,"minecraft:sticky_piston":120,"minecraft:cobbled_deepslate":189,"minecraft:barrel":6,"minecraft:fire":216,"minecraft:deepslate_lapis_ore":17,"minecraft:granite_slab":24,"minecraft:pumpkin":61,"minecraft:fletching_table":3,"minecraft:oak_sign":5,"minecraft:polished_deepslate_slab":216,"minecraft:dirt_path":1401,"minecraft:oak_stairs":266,"minecraft:deepslate_brick_stairs":164,"minecraft:pink_tulip":8,"minecraft:white_shulker_box":3,"minecraft:white_banner":1,"minecraft:iron_block":37,"minecraft:tripwire":27,"minecraft:piston_head":7,"minecraft:blue_concrete_powder":8,"minecraft:red_bed":1,"minecraft:crimson_nylium":108,"minecraft:kelp_plant":46,"minecraft:smoker":1,"minecraft:deepslate_brick_wall":23,"minecraft:deepslate_tile_slab":100,"minecraft:torch":74,"minecraft:note_block":10,"minecraft:blast_furnace":1,"minecraft:white_stained_glass_pane":4,"minecraft:nether_brick_slab":7,"minecraft:spruce_wall_sign":7,"minecraft:glass":977,"minecraft:sugar_cane":760,"minecraft:spruce_sign":4,"minecraft:birch_sapling":1,"minecraft:white_terracotta":93,"minecraft:chain":2,"minecraft:repeater":49,"minecraft:black_concrete_powder":9,"minecraft:wheat":128,"minecraft:lilac":12,"minecraft:lime_concrete":2,"minecraft:stone_brick_stairs":170,"minecraft:grass":900,"minecraft:oak_fence_gate":128,"minecraft:loom":1,"minecraft:blue_shulker_box":26,"minecraft:red_mushroom_block":226,"minecraft:stonecutter":30,"minecraft:piston":49,"minecraft:deepslate":6592,"minecraft:deepslate_tiles":117,"minecraft:pink_shulker_box":25,"minecraft:mossy_cobblestone":48,"minecraft:orange_concrete_powder":2,"minecraft:dark_oak_log":33,"minecraft:cobbled_deepslate_slab":1,"minecraft:end_stone":1916,"minecraft:nether_bricks":603,"minecraft:shulker_box":61,"minecraft:allium":2,"minecraft:dark_oak_fence":8,"minecraft:spruce_fence":19,"minecraft:jungle_planks":2,"minecraft:crimson_roots":4,"minecraft:orange_shulker_box":158,"minecraft:redstone_wire":198,"minecraft:yellow_concrete_powder":1,"minecraft:kelp":87,"minecraft:cartography_table":1,"minecraft:white_concrete_powder":3,"minecraft:redstone_ore":16,"minecraft:light_blue_concrete_powder":7,"minecraft:andesite":193,"minecraft:potatoes":3,"minecraft:magenta_concrete_powder":3,"minecraft:vine":22,"minecraft:rail":603,"minecraft:cobblestone_slab":82,"minecraft:warped_stem":2,"minecraft:bamboo":92,"minecraft:bone_block":8,"minecraft:ender_chest":41,"minecraft:smithing_table":1,"minecraft:birch_stairs":2,"minecraft:oak_slab":43,"minecraft:redstone_block":29,"minecraft:glass_pane":36,"minecraft:comparator":28,"minecraft:soul_sand":18,"minecraft:lily_of_the_valley":13,"minecraft:stone_brick_slab":50,"minecraft:pink_concrete_powder":3,"minecraft:observer":94,"minecraft:dandelion":12,"minecraft:light_gray_concrete_powder":5,"minecraft:cornflower":14,"minecraft:spruce_button":1,"minecraft:dead_tube_coral_wall_fan":1,"minecraft:dropper":4,"minecraft:warped_roots":1,"minecraft:copper_ore":90,"minecraft:lightning_rod":3,"minecraft:tall_grass":135,"minecraft:purpur_pillar":2,"minecraft:deepslate_gold_ore":6,"minecraft:diorite":57,"minecraft:warped_wart_block":6,"minecraft:cobblestone_wall":17,"minecraft:white_carpet":11,"minecraft:spruce_log":4652,"minecraft:birch_leaves":105,"minecraft:gravel":256,"minecraft:dripstone_block":54,"minecraft:cobweb":1,"minecraft:spruce_fence_gate":38,"minecraft:stone_bricks":4835,"minecraft:gold_ore":9,"minecraft:chipped_anvil":1,"minecraft:iron_trapdoor":6,"minecraft:infested_stone":1,"minecraft:fern":3,"minecraft:spruce_planks":411,"minecraft:farmland":77,"minecraft:oak_sapling":2,"minecraft:stone_pressure_plate":10,"minecraft:mossy_stone_brick_slab":3,"minecraft:cobblestone_stairs":22,"minecraft:brewing_stand":8,"minecraft:spruce_trapdoor":240,"minecraft:grass_block":11189,"minecraft:blue_concrete":543,"minecraft:polished_diorite":5,"minecraft:composter":13,"minecraft:smooth_stone":468,"minecraft:glowstone":28,"minecraft:iron_ore":75,"minecraft:target":9,"minecraft:potted_red_mushroom":1,"minecraft:dragon_head":1,"minecraft:azure_bluet":4,"minecraft:dark_oak_stairs":1,"minecraft:pointed_dripstone":27,"minecraft:red_tulip":14,"minecraft:iron_bars":43,"minecraft:end_stone_bricks":12,"minecraft:spruce_slab":347,"minecraft:netherite_block":2,"minecraft:deepslate_redstone_ore":32,"minecraft:quartz_block":59,"minecraft:blackstone":246,"minecraft:twisting_vines_plant":1,"minecraft:purpur_stairs":4,"minecraft:clay":14,"minecraft:jungle_stairs":2,"minecraft:end_stone_brick_slab":5,"minecraft:poppy":7,"minecraft:chest":389,"minecraft:beacon":3,"minecraft:mushroom_stem":35,"minecraft:nether_quartz_ore":269,"minecraft:cobblestone":2313,"minecraft:slime_block":207,"minecraft:grindstone":2,"minecraft:oak_planks":442,"minecraft:iron_door":2,"minecraft:wall_torch":24,"minecraft:cauldron":2,"minecraft:deepslate_copper_ore":14,"minecraft:magenta_shulker_box":48,"minecraft:pink_petals":6,"minecraft:seagrass":10,"minecraft:warped_nylium":7,"minecraft:powered_rail":238,"minecraft:nether_wart_block":21,"minecraft:birch_log":150,"minecraft:stripped_oak_wood":2,"minecraft:tnt":16,"minecraft:orange_tulip":20,"minecraft:purpur_block":20,"minecraft:smooth_stone_slab":30,"minecraft:yellow_stained_glass_pane":5,"minecraft:oak_log":1212,"minecraft:beetroots":2,"minecraft:sand":1944,"minecraft:dirt":8118,"minecraft:infested_cracked_stone_bricks":1,"minecraft:dispenser":2,"minecraft:tripwire_hook":7,"minecraft:wither_skeleton_skull":1,"minecraft:netherrack":8309,"minecraft:ancient_debris":3,"minecraft:oak_leaves":615,"minecraft:redstone_lamp":5,"minecraft:nether_gold_ore":64,"minecraft:tuff":87,"minecraft:oak_door":6,"minecraft:deepslate_diamond_ore":6,"minecraft:lever":37,"minecraft:ladder":3,"minecraft:weeping_vines":3,"minecraft:white_stained_glass":4,"minecraft:brown_mushroom_block":7,"minecraft:birch_slab":3,"minecraft:spruce_leaves":528,"minecraft:dead_horn_coral_wall_fan":31,"minecraft:crimson_stem":4,"minecraft:deepslate_brick_slab":134,"minecraft:diorite_slab":21,"minecraft:oak_trapdoor":51,"minecraft:spruce_sapling":21,"minecraft:furnace":121,"minecraft:carrots":23,"minecraft:red_concrete_powder":8,"minecraft:light_gray_shulker_box":91,"minecraft:stripped_spruce_log":54,"minecraft:black_concrete":142,"minecraft:chiseled_deepslate":2,"minecraft:detector_rail":95,"minecraft:peony":13,"minecraft:gold_block":189,"minecraft:dead_horn_coral_block":1,"minecraft:bell":2,"minecraft:nether_brick_fence":33,"minecraft:polished_deepslate":359,"minecraft:bookshelf":1,"minecraft:shroomlight":4,"minecraft:deepslate_iron_ore":6,"minecraft:lantern":9,"minecraft:stripped_oak_log":4,"minecraft:packed_ice":66,"minecraft:white_tulip":10,"minecraft:stone":10722,"minecraft:yellow_shulker_box":8,"minecraft:redstone_wall_torch":12,"minecraft:podzol":368,"minecraft:scaffolding":455,"minecraft:magenta_stained_glass":2,"minecraft:infested_stone_bricks":25,"minecraft:basalt":215,"minecraft:spruce_door":6,"minecraft:oak_fence":22,"minecraft:crafting_table":74,"minecraft:blackstone_slab":1,"minecraft:lime_concrete_powder":6,"minecraft:rose_bush":3,"minecraft:andesite_slab":1,"minecraft:lectern":197,"minecraft:stone_slab":10,"minecraft:quartz_bricks":2,"minecraft:lapis_ore":4,"minecraft:lily_pad":20,"minecraft:spruce_stairs":166,"minecraft:birch_planks":2,"minecraft:redstone_torch":37,"minecraft:yellow_bed":13,"minecraft:coal_ore":178,"minecraft:yellow_concrete":561,"minecraft:cracked_stone_bricks":121,"minecraft:terracotta":2,"minecraft:mossy_stone_bricks":192},"minecraft:broken":{"minecraft:diamond_helmet":1,"minecraft:fishing_rod":1,"minecraft:diamond_leggings":1,"minecraft:iron_axe":9,"minecraft:iron_pickaxe":1,"minecraft:iron_shovel":3,"minecraft:stone_pickaxe":1,"minecraft:flint_and_steel":3},"minecraft:custom":{"minecraft:interact_with_crafting_table":756,"minecraft:eat_cake_slice":9,"minecraft:leave_game":124,"minecraft:time_since_death":4498581,"minecraft:damage_blocked_by_shield":5200,"minecraft:play_time":7726391,"minecraft:deaths":17,"minecraft:jump":92062,"minecraft:enchant_item":41,"minecraft:interact_with_furnace":1298,"minecraft:traded_with_villager":849,"minecraft:sleep_in_bed":158,"minecraft:damage_dealt":259562,"minecraft:inspect_dispenser":65,"minecraft:use_cauldron":10,"minecraft:horse_one_cm":83654,"minecraft:interact_with_smithing_table":2,"minecraft:inspect_dropper":37,"minecraft:interact_with_anvil":60,"minecraft:inspect_hopper":1438,"minecraft:damage_dealt_absorbed":182,"minecraft:sneak_time":719189,"minecraft:interact_with_blast_furnace":12,"minecraft:total_world_time":7726391,"minecraft:tune_noteblock":21,"minecraft:interact_with_stonecutter":115,"minecraft:time_since_rest":73904,"minecraft:swim_one_cm":654108,"minecraft:fly_one_cm":21739515,"minecraft:open_chest":8637,"minecraft:fall_one_cm":2191289,"minecraft:open_shulker_box":3044,"minecraft:damage_resisted":362,"minecraft:sprint_one_cm":15329619,"minecraft:drop":4367,"minecraft:play_noteblock":26,"minecraft:talked_to_villager":841,"minecraft:interact_with_brewingstand":54,"minecraft:walk_on_water_one_cm":918779,"minecraft:interact_with_loom":10,"minecraft:open_enderchest":179,"minecraft:interact_with_beacon":5,"minecraft:player_kills":2,"minecraft:crouch_one_cm":2903164,"minecraft:mob_kills":13829,"minecraft:climb_one_cm":775975,"minecraft:walk_one_cm":17084792,"minecraft:walk_under_water_one_cm":450806,"minecraft:boat_one_cm":2322729,"minecraft:raid_trigger":2,"minecraft:interact_with_grindstone":24,"minecraft:damage_taken":61350,"minecraft:damage_absorbed":173,"minecraft:minecart_one_cm":568133,"minecraft:aviate_one_cm":43835265}},"DataVersion":3465}